MANIFEST.in
README
presenter
setup.cfg
setup.py
Presenter.egg-info/PKG-INFO
Presenter.egg-info/SOURCES.txt
Presenter.egg-info/dependency_links.txt
Presenter.egg-info/entry_points.txt
Presenter.egg-info/top_level.txt
presenter/__init__.py
presenter/control.py
presenter/fakegio.py
presenter/interface.glade
presenter/interface.py
presenter/monitordialog.py
presenter/monitorwidget.py
presenter/output.py
presenter/runsheet.py
presenter/handlers/__init__.py
presenter/handlers/base.py
presenter/handlers/evince_handler.py
presenter/handlers/video_handler.py
scripts/presenter