Metadata-Version: 1.0
Name: Presenter
Version: 0.2dev
Summary: The presentation tool designed for control freaks.
Home-page: http://flowblok.selfip.net:8001/trac/presenter/
Author: Peter Ward
Author-email: peteraward@gmail.com
License: GNU General Public License (GPL)
Platform: UNKNOWN
Classifier: Development Status :: 3 - Alpha
Classifier: Environment :: X11 Applications :: GTK
Classifier: Intended Audience :: End Users/Desktop
Classifier: License :: OSI Approved :: GNU General Public License (GPL)
Classifier: Operating System :: POSIX :: Linux
Classifier: Operating System :: Microsoft :: Windows
Classifier: Programming Language :: Python :: 2.5
Classifier: Topic :: Multimedia :: Graphics :: Presentation
Classifier: Topic :: Multimedia :: Video :: Display
